howsit/__init__.py
howsit/__main__.py
howsit/_version.py
howsit/main.py
howsit/parse.py
howsit/test/__init__.py
howsit/test/self_test.py
howsit/test/test_parse.py
howsit-20.6.0.dist-info/METADATA
howsit-20.6.0.dist-info/WHEEL
howsit-20.6.0.dist-info/top_level.txt
howsit-20.6.0.dist-info/RECORD
