Metadata-Version: 2.1
Name: howsit
Version: 20.6.0
Summary: Howsit: how bad is git today?
Home-page: UNKNOWN
Author: Moshe Zadka
Author-email: zadka.moshe@gmail.com
License: MIT
Platform: UNKNOWN
Requires-Dist: attrs
Requires-Dist: incremental
Requires-Dist: seashore
Requires-Dist: enum34 ; python_version < "3.4"
